pr0gramm/__init__.py
pr0gramm/api.py
pr0gramm/api_exceptions.py
pr0gramm/items.py
pr0gramm/pr0gramm_sqlite.sql
pr0gramm/sql_manager.py
pypr0-0.2.8.dist-info/LICENSE
pypr0-0.2.8.dist-info/METADATA
pypr0-0.2.8.dist-info/WHEEL
pypr0-0.2.8.dist-info/top_level.txt
pypr0-0.2.8.dist-info/RECORD
