Metadata-Version: 2.1
Name: pypr0
Version: 0.2.8
Summary: Implementation of the pr0gramm api in python
Home-page: https://github.com/itssme/pypr0
Author: itssme
Author-email: itssme3000@gmail.com
License: GNU GPLv3
Classifier: Programming Language :: Python :: 3.7
Classifier: License :: OSI Approved :: GNU General Public License v3 (GPLv3)
Classifier: Operating System :: OS Independent
License-File: LICENSE
Requires-Dist: requests
